[{"YYYYMMDD": "20150101", "STN": "260", "TG": "30"}, {"YYYYMMDD": "20150102", "STN": "260", "TG": "73"}, {"YYYYMMDD": "20150103", "STN": "260", "TG": "38"}, {"YYYYMMDD": "20150104", "STN": "260", "TG": "39"}, {"YYYYMMDD": "20150105", "STN": "260", "TG": "24"}, {"YYYYMMDD": "20150106", "STN": "260", "TG": "28"}, {"YYYYMMDD": "20150107", "STN": "260", "TG": "45"}, {"YYYYMMDD": "20150108", "STN": "260", "TG": "65"}, {"YYYYMMDD": "20150109", "STN": "260", "TG": "99"}, {"YYYYMMDD": "20150110", "STN": "260", "TG": "95"}, {"YYYYMMDD": "20150111", "STN": "260", "TG": "64"}, {"YYYYMMDD": "20150112", "STN": "260", "TG": "84"}, {"YYYYMMDD": "20150113", "STN": "260", "TG": "86"}, {"YYYYMMDD": "20150114", "STN": "260", "TG": "44"}, {"YYYYMMDD": "20150115", "STN": "260", "TG": "79"}, {"YYYYMMDD": "20150116", "STN": "260", "TG": "55"}, {"YYYYMMDD": "20150117", "STN": "260", "TG": "30"}, {"YYYYMMDD": "20150118", "STN": "260", "TG": "22"}, {"YYYYMMDD": "20150119", "STN": "260", "TG": "10"}, {"YYYYMMDD": "20150120", "STN": "260", "TG": "8"}, {"YYYYMMDD": "20150121", "STN": "260", "TG": "-5"}, {"YYYYMMDD": "20150122", "STN": "260", "TG": "-12"}, {"YYYYMMDD": "20150123", "STN": "260", "TG": "-28"}, {"YYYYMMDD": "20150124", "STN": "260", "TG": "22"}, {"YYYYMMDD": "20150125", "STN": "260", "TG": "37"}, {"YYYYMMDD": "20150126", "STN": "260", "TG": "59"}, {"YYYYMMDD": "20150127", "STN": "260", "TG": "51"}, {"YYYYMMDD": "20150128", "STN": "260", "TG": "53"}, {"YYYYMMDD": "20150129", "STN": "260", "TG": "24"}, {"YYYYMMDD": "20150130", "STN": "260", "TG": "17"}, {"YYYYMMDD": "20150131", "STN": "260", "TG": "10"}, {"YYYYMMDD": "20150201", "STN": "260", "TG": "26"}, {"YYYYMMDD": "20150202", "STN": "260", "TG": "20"}, {"YYYYMMDD": "20150203", "STN": "260", "TG": "17"}, {"YYYYMMDD": "20150204", "STN": "260", "TG": "2"}, {"YYYYMMDD": "20150205", "STN": "260", "TG": "-7"}, {"YYYYMMDD": "20150206", "STN": "260", "TG": "-2"}, {"YYYYMMDD": "20150207", "STN": "260", "TG": "15"}, {"YYYYMMDD": "20150208", "STN": "260", "TG": "50"}, {"YYYYMMDD": "20150209", "STN": "260", "TG": "57"}, {"YYYYMMDD": "20150210", "STN": "260", "TG": "57"}, {"YYYYMMDD": "20150211", "STN": "260", "TG": "42"}, {"YYYYMMDD": "20150212", "STN": "260", "TG": "26"}, {"YYYYMMDD": "20150213", "STN": "260", "TG": "46"}, {"YYYYMMDD": "20150214", "STN": "260", "TG": "66"}, {"YYYYMMDD": "20150215", "STN": "260", "TG": "26"}, {"YYYYMMDD": "20150216", "STN": "260", "TG": "9"}, {"YYYYMMDD": "20150217", "STN": "260", "TG": "33"}, {"YYYYMMDD": "20150218", "STN": "260", "TG": "18"}, {"YYYYMMDD": "20150219", "STN": "260", "TG": "35"}, {"YYYYMMDD": "20150220", "STN": "260", "TG": "53"}, {"YYYYMMDD": "20150221", "STN": "260", "TG": "32"}, {"YYYYMMDD": "20150222", "STN": "260", "TG": "32"}, {"YYYYMMDD": "20150223", "STN": "260", "TG": "59"}, {"YYYYMMDD": "20150224", "STN": "260", "TG": "54"}, {"YYYYMMDD": "20150225", "STN": "260", "TG": "48"}, {"YYYYMMDD": "20150226", "STN": "260", "TG": "63"}, {"YYYYMMDD": "20150227", "STN": "260", "TG": "49"}, {"YYYYMMDD": "20150228", "STN": "260", "TG": "51"}, {"YYYYMMDD": "20150301", "STN": "260", "TG": "83"}, {"YYYYMMDD": "20150302", "STN": "260", "TG": "53"}, {"YYYYMMDD": "20150303", "STN": "260", "TG": "44"}, {"YYYYMMDD": "20150304", "STN": "260", "TG": "51"}, {"YYYYMMDD": "20150305", "STN": "260", "TG": "57"}, {"YYYYMMDD": "20150306", "STN": "260", "TG": "66"}, {"YYYYMMDD": "20150307", "STN": "260", "TG": "84"}, {"YYYYMMDD": "20150308", "STN": "260", "TG": "93"}, {"YYYYMMDD": "20150309", "STN": "260", "TG": "88"}, {"YYYYMMDD": "20150310", "STN": "260", "TG": "76"}, {"YYYYMMDD": "20150311", "STN": "260", "TG": "27"}, {"YYYYMMDD": "20150312", "STN": "260", "TG": "54"}, {"YYYYMMDD": "20150313", "STN": "260", "TG": "46"}, {"YYYYMMDD": "20150314", "STN": "260", "TG": "34"}, {"YYYYMMDD": "20150315", "STN": "260", "TG": "56"}, {"YYYYMMDD": "20150316", "STN": "260", "TG": "63"}, {"YYYYMMDD": "20150317", "STN": "260", "TG": "76"}, {"YYYYMMDD": "20150318", "STN": "260", "TG": "56"}, {"YYYYMMDD": "20150319", "STN": "260", "TG": "68"}, {"YYYYMMDD": "20150320", "STN": "260", "TG": "49"}, {"YYYYMMDD": "20150321", "STN": "260", "TG": "64"}, {"YYYYMMDD": "20150322", "STN": "260", "TG": "43"}, {"YYYYMMDD": "20150323", "STN": "260", "TG": "31"}, {"YYYYMMDD": "20150324", "STN": "260", "TG": "57"}, {"YYYYMMDD": "20150325", "STN": "260", "TG": "59"}, {"YYYYMMDD": "20150326", "STN": "260", "TG": "50"}, {"YYYYMMDD": "20150327", "STN": "260", "TG": "57"}, {"YYYYMMDD": "20150328", "STN": "260", "TG": "69"}, {"YYYYMMDD": "20150329", "STN": "260", "TG": "93"}, {"YYYYMMDD": "20150330", "STN": "260", "TG": "72"}, {"YYYYMMDD": "20150331", "STN": "260", "TG": "90"}, {"YYYYMMDD": "20150401", "STN": "260", "TG": "65"}, {"YYYYMMDD": "20150402", "STN": "260", "TG": "63"}, {"YYYYMMDD": "20150403", "STN": "260", "TG": "70"}, {"YYYYMMDD": "20150404", "STN": "260", "TG": "54"}, {"YYYYMMDD": "20150405", "STN": "260", "TG": "53"}, {"YYYYMMDD": "20150406", "STN": "260", "TG": "69"}, {"YYYYMMDD": "20150407", "STN": "260", "TG": "71"}, {"YYYYMMDD": "20150408", "STN": "260", "TG": "86"}, {"YYYYMMDD": "20150409", "STN": "260", "TG": "104"}, {"YYYYMMDD": "20150410", "STN": "260", "TG": "113"}, {"YYYYMMDD": "20150411", "STN": "260", "TG": "90"}, {"YYYYMMDD": "20150412", "STN": "260", "TG": "100"}, {"YYYYMMDD": "20150413", "STN": "260", "TG": "84"}, {"YYYYMMDD": "20150414", "STN": "260", "TG": "119"}, {"YYYYMMDD": "20150415", "STN": "260", "TG": "138"}, {"YYYYMMDD": "20150416", "STN": "260", "TG": "99"}, {"YYYYMMDD": "20150417", "STN": "260", "TG": "85"}, {"YYYYMMDD": "20150418", "STN": "260", "TG": "90"}, {"YYYYMMDD": "20150419", "STN": "260", "TG": "78"}, {"YYYYMMDD": "20150420", "STN": "260", "TG": "109"}, {"YYYYMMDD": "20150421", "STN": "260", "TG": "100"}, {"YYYYMMDD": "20150422", "STN": "260", "TG": "85"}, {"YYYYMMDD": "20150423", "STN": "260", "TG": "94"}, {"YYYYMMDD": "20150424", "STN": "260", "TG": "124"}, {"YYYYMMDD": "20150425", "STN": "260", "TG": "121"}, {"YYYYMMDD": "20150426", "STN": "260", "TG": "106"}, {"YYYYMMDD": "20150427", "STN": "260", "TG": "80"}, {"YYYYMMDD": "20150428", "STN": "260", "TG": "60"}, {"YYYYMMDD": "20150429", "STN": "260", "TG": "89"}, {"YYYYMMDD": "20150430", "STN": "260", "TG": "98"}, {"YYYYMMDD": "20150501", "STN": "260", "TG": "87"}, {"YYYYMMDD": "20150502", "STN": "260", "TG": "97"}, {"YYYYMMDD": "20150503", "STN": "260", "TG": "130"}, {"YYYYMMDD": "20150504", "STN": "260", "TG": "154"}, {"YYYYMMDD": "20150505", "STN": "260", "TG": "154"}, {"YYYYMMDD": "20150506", "STN": "260", "TG": "122"}, {"YYYYMMDD": "20150507", "STN": "260", "TG": "118"}, {"YYYYMMDD": "20150508", "STN": "260", "TG": "142"}, {"YYYYMMDD": "20150509", "STN": "260", "TG": "133"}, {"YYYYMMDD": "20150510", "STN": "260", "TG": "128"}, {"YYYYMMDD": "20150511", "STN": "260", "TG": "176"}, {"YYYYMMDD": "20150512", "STN": "260", "TG": "146"}, {"YYYYMMDD": "20150513", "STN": "260", "TG": "127"}, {"YYYYMMDD": "20150514", "STN": "260", "TG": "112"}, {"YYYYMMDD": "20150515", "STN": "260", "TG": "94"}, {"YYYYMMDD": "20150516", "STN": "260", "TG": "105"}, {"YYYYMMDD": "20150517", "STN": "260", "TG": "119"}, {"YYYYMMDD": "20150518", "STN": "260", "TG": "111"}, {"YYYYMMDD": "20150519", "STN": "260", "TG": "100"}, {"YYYYMMDD": "20150520", "STN": "260", "TG": "105"}, {"YYYYMMDD": "20150521", "STN": "260", "TG": "119"}, {"YYYYMMDD": "20150522", "STN": "260", "TG": "149"}, {"YYYYMMDD": "20150523", "STN": "260", "TG": "124"}, {"YYYYMMDD": "20150524", "STN": "260", "TG": "126"}, {"YYYYMMDD": "20150525", "STN": "260", "TG": "124"}, {"YYYYMMDD": "20150526", "STN": "260", "TG": "118"}, {"YYYYMMDD": "20150527", "STN": "260", "TG": "135"}, {"YYYYMMDD": "20150528", "STN": "260", "TG": "129"}, {"YYYYMMDD": "20150529", "STN": "260", "TG": "111"}, {"YYYYMMDD": "20150530", "STN": "260", "TG": "112"}, {"YYYYMMDD": "20150531", "STN": "260", "TG": "126"}, {"YYYYMMDD": "20150601", "STN": "260", "TG": "127"}, {"YYYYMMDD": "20150602", "STN": "260", "TG": "148"}, {"YYYYMMDD": "20150603", "STN": "260", "TG": "138"}, {"YYYYMMDD": "20150604", "STN": "260", "TG": "156"}, {"YYYYMMDD": "20150605", "STN": "260", "TG": "214"}, {"YYYYMMDD": "20150606", "STN": "260", "TG": "156"}, {"YYYYMMDD": "20150607", "STN": "260", "TG": "139"}, {"YYYYMMDD": "20150608", "STN": "260", "TG": "125"}, {"YYYYMMDD": "20150609", "STN": "260", "TG": "116"}, {"YYYYMMDD": "20150610", "STN": "260", "TG": "154"}, {"YYYYMMDD": "20150611", "STN": "260", "TG": "179"}, {"YYYYMMDD": "20150612", "STN": "260", "TG": "216"}, {"YYYYMMDD": "20150613", "STN": "260", "TG": "175"}, {"YYYYMMDD": "20150614", "STN": "260", "TG": "153"}, {"YYYYMMDD": "20150615", "STN": "260", "TG": "133"}, {"YYYYMMDD": "20150616", "STN": "260", "TG": "114"}, {"YYYYMMDD": "20150617", "STN": "260", "TG": "160"}, {"YYYYMMDD": "20150618", "STN": "260", "TG": "143"}, {"YYYYMMDD": "20150619", "STN": "260", "TG": "127"}, {"YYYYMMDD": "20150620", "STN": "260", "TG": "130"}, {"YYYYMMDD": "20150621", "STN": "260", "TG": "144"}, {"YYYYMMDD": "20150622", "STN": "260", "TG": "127"}, {"YYYYMMDD": "20150623", "STN": "260", "TG": "126"}, {"YYYYMMDD": "20150624", "STN": "260", "TG": "158"}, {"YYYYMMDD": "20150625", "STN": "260", "TG": "182"}, {"YYYYMMDD": "20150626", "STN": "260", "TG": "205"}, {"YYYYMMDD": "20150627", "STN": "260", "TG": "176"}, {"YYYYMMDD": "20150628", "STN": "260", "TG": "173"}, {"YYYYMMDD": "20150629", "STN": "260", "TG": "180"}, {"YYYYMMDD": "20150630", "STN": "260", "TG": "206"}, {"YYYYMMDD": "20150701", "STN": "260", "TG": "260"}, {"YYYYMMDD": "20150702", "STN": "260", "TG": "254"}, {"YYYYMMDD": "20150703", "STN": "260", "TG": "241"}, {"YYYYMMDD": "20150704", "STN": "260", "TG": "256"}, {"YYYYMMDD": "20150705", "STN": "260", "TG": "202"}, {"YYYYMMDD": "20150706", "STN": "260", "TG": "187"}, {"YYYYMMDD": "20150707", "STN": "260", "TG": "198"}, {"YYYYMMDD": "20150708", "STN": "260", "TG": "159"}, {"YYYYMMDD": "20150709", "STN": "260", "TG": "135"}, {"YYYYMMDD": "20150710", "STN": "260", "TG": "165"}, {"YYYYMMDD": "20150711", "STN": "260", "TG": "204"}, {"YYYYMMDD": "20150712", "STN": "260", "TG": "177"}, {"YYYYMMDD": "20150713", "STN": "260", "TG": "174"}, {"YYYYMMDD": "20150714", "STN": "260", "TG": "179"}, {"YYYYMMDD": "20150715", "STN": "260", "TG": "179"}, {"YYYYMMDD": "20150716", "STN": "260", "TG": "196"}, {"YYYYMMDD": "20150717", "STN": "260", "TG": "217"}, {"YYYYMMDD": "20150718", "STN": "260", "TG": "182"}, {"YYYYMMDD": "20150719", "STN": "260", "TG": "162"}, {"YYYYMMDD": "20150720", "STN": "260", "TG": "178"}, {"YYYYMMDD": "20150721", "STN": "260", "TG": "210"}, {"YYYYMMDD": "20150722", "STN": "260", "TG": "195"}, {"YYYYMMDD": "20150723", "STN": "260", "TG": "178"}, {"YYYYMMDD": "20150724", "STN": "260", "TG": "184"}, {"YYYYMMDD": "20150725", "STN": "260", "TG": "149"}, {"YYYYMMDD": "20150726", "STN": "260", "TG": "148"}, {"YYYYMMDD": "20150727", "STN": "260", "TG": "166"}, {"YYYYMMDD": "20150728", "STN": "260", "TG": "152"}, {"YYYYMMDD": "20150729", "STN": "260", "TG": "141"}, {"YYYYMMDD": "20150730", "STN": "260", "TG": "138"}, {"YYYYMMDD": "20150731", "STN": "260", "TG": "133"}, {"YYYYMMDD": "20150801", "STN": "260", "TG": "151"}, {"YYYYMMDD": "20150802", "STN": "260", "TG": "177"}, {"YYYYMMDD": "20150803", "STN": "260", "TG": "215"}, {"YYYYMMDD": "20150804", "STN": "260", "TG": "180"}, {"YYYYMMDD": "20150805", "STN": "260", "TG": "189"}, {"YYYYMMDD": "20150806", "STN": "260", "TG": "205"}, {"YYYYMMDD": "20150807", "STN": "260", "TG": "206"}, {"YYYYMMDD": "20150808", "STN": "260", "TG": "187"}, {"YYYYMMDD": "20150809", "STN": "260", "TG": "186"}, {"YYYYMMDD": "20150810", "STN": "260", "TG": "198"}, {"YYYYMMDD": "20150811", "STN": "260", "TG": "200"}, {"YYYYMMDD": "20150812", "STN": "260", "TG": "195"}, {"YYYYMMDD": "20150813", "STN": "260", "TG": "217"}, {"YYYYMMDD": "20150814", "STN": "260", "TG": "209"}, {"YYYYMMDD": "20150815", "STN": "260", "TG": "184"}, {"YYYYMMDD": "20150816", "STN": "260", "TG": "150"}, {"YYYYMMDD": "20150817", "STN": "260", "TG": "143"}, {"YYYYMMDD": "20150818", "STN": "260", "TG": "146"}, {"YYYYMMDD": "20150819", "STN": "260", "TG": "165"}, {"YYYYMMDD": "20150820", "STN": "260", "TG": "179"}, {"YYYYMMDD": "20150821", "STN": "260", "TG": "197"}, {"YYYYMMDD": "20150822", "STN": "260", "TG": "207"}, {"YYYYMMDD": "20150823", "STN": "260", "TG": "197"}, {"YYYYMMDD": "20150824", "STN": "260", "TG": "179"}, {"YYYYMMDD": "20150825", "STN": "260", "TG": "167"}, {"YYYYMMDD": "20150826", "STN": "260", "TG": "202"}, {"YYYYMMDD": "20150827", "STN": "260", "TG": "157"}, {"YYYYMMDD": "20150828", "STN": "260", "TG": "154"}, {"YYYYMMDD": "20150829", "STN": "260", "TG": "170"}, {"YYYYMMDD": "20150830", "STN": "260", "TG": "200"}, {"YYYYMMDD": "20150831", "STN": "260", "TG": "209"}, {"YYYYMMDD": "20150901", "STN": "260", "TG": "161"}, {"YYYYMMDD": "20150902", "STN": "260", "TG": "132"}, {"YYYYMMDD": "20150903", "STN": "260", "TG": "122"}, {"YYYYMMDD": "20150904", "STN": "260", "TG": "135"}, {"YYYYMMDD": "20150905", "STN": "260", "TG": "132"}, {"YYYYMMDD": "20150906", "STN": "260", "TG": "131"}, {"YYYYMMDD": "20150907", "STN": "260", "TG": "142"}, {"YYYYMMDD": "20150908", "STN": "260", "TG": "139"}, {"YYYYMMDD": "20150909", "STN": "260", "TG": "131"}, {"YYYYMMDD": "20150910", "STN": "260", "TG": "143"}, {"YYYYMMDD": "20150911", "STN": "260", "TG": "143"}, {"YYYYMMDD": "20150912", "STN": "260", "TG": "157"}, {"YYYYMMDD": "20150913", "STN": "260", "TG": "166"}, {"YYYYMMDD": "20150914", "STN": "260", "TG": "145"}, {"YYYYMMDD": "20150915", "STN": "260", "TG": "125"}, {"YYYYMMDD": "20150916", "STN": "260", "TG": "154"}, {"YYYYMMDD": "20150917", "STN": "260", "TG": "144"}, {"YYYYMMDD": "20150918", "STN": "260", "TG": "139"}, {"YYYYMMDD": "20150919", "STN": "260", "TG": "134"}, {"YYYYMMDD": "20150920", "STN": "260", "TG": "135"}, {"YYYYMMDD": "20150921", "STN": "260", "TG": "146"}, {"YYYYMMDD": "20150922", "STN": "260", "TG": "131"}, {"YYYYMMDD": "20150923", "STN": "260", "TG": "132"}, {"YYYYMMDD": "20150924", "STN": "260", "TG": "126"}, {"YYYYMMDD": "20150925", "STN": "260", "TG": "116"}, {"YYYYMMDD": "20150926", "STN": "260", "TG": "104"}, {"YYYYMMDD": "20150927", "STN": "260", "TG": "110"}, {"YYYYMMDD": "20150928", "STN": "260", "TG": "105"}, {"YYYYMMDD": "20150929", "STN": "260", "TG": "117"}, {"YYYYMMDD": "20150930", "STN": "260", "TG": "123"}, {"YYYYMMDD": "20151001", "STN": "260", "TG": "106"}, {"YYYYMMDD": "20151002", "STN": "260", "TG": "103"}, {"YYYYMMDD": "20151003", "STN": "260", "TG": "103"}, {"YYYYMMDD": "20151004", "STN": "260", "TG": "103"}, {"YYYYMMDD": "20151005", "STN": "260", "TG": "131"}, {"YYYYMMDD": "20151006", "STN": "260", "TG": "153"}, {"YYYYMMDD": "20151007", "STN": "260", "TG": "149"}, {"YYYYMMDD": "20151008", "STN": "260", "TG": "124"}, {"YYYYMMDD": "20151009", "STN": "260", "TG": "102"}, {"YYYYMMDD": "20151010", "STN": "260", "TG": "109"}, {"YYYYMMDD": "20151011", "STN": "260", "TG": "65"}, {"YYYYMMDD": "20151012", "STN": "260", "TG": "48"}, {"YYYYMMDD": "20151013", "STN": "260", "TG": "38"}, {"YYYYMMDD": "20151014", "STN": "260", "TG": "51"}, {"YYYYMMDD": "20151015", "STN": "260", "TG": "63"}, {"YYYYMMDD": "20151016", "STN": "260", "TG": "77"}, {"YYYYMMDD": "20151017", "STN": "260", "TG": "81"}, {"YYYYMMDD": "20151018", "STN": "260", "TG": "84"}, {"YYYYMMDD": "20151019", "STN": "260", "TG": "105"}, {"YYYYMMDD": "20151020", "STN": "260", "TG": "95"}, {"YYYYMMDD": "20151021", "STN": "260", "TG": "97"}, {"YYYYMMDD": "20151022", "STN": "260", "TG": "119"}, {"YYYYMMDD": "20151023", "STN": "260", "TG": "114"}, {"YYYYMMDD": "20151024", "STN": "260", "TG": "118"}, {"YYYYMMDD": "20151025", "STN": "260", "TG": "99"}, {"YYYYMMDD": "20151026", "STN": "260", "TG": "105"}, {"YYYYMMDD": "20151027", "STN": "260", "TG": "111"}, {"YYYYMMDD": "20151028", "STN": "260", "TG": "106"}, {"YYYYMMDD": "20151029", "STN": "260", "TG": "107"}, {"YYYYMMDD": "20151030", "STN": "260", "TG": "102"}, {"YYYYMMDD": "20151031", "STN": "260", "TG": "98"}, {"YYYYMMDD": "20151101", "STN": "260", "TG": "77"}, {"YYYYMMDD": "20151102", "STN": "260", "TG": "69"}, {"YYYYMMDD": "20151103", "STN": "260", "TG": "90"}, {"YYYYMMDD": "20151104", "STN": "260", "TG": "122"}, {"YYYYMMDD": "20151105", "STN": "260", "TG": "133"}, {"YYYYMMDD": "20151106", "STN": "260", "TG": "155"}, {"YYYYMMDD": "20151107", "STN": "260", "TG": "164"}, {"YYYYMMDD": "20151108", "STN": "260", "TG": "131"}, {"YYYYMMDD": "20151109", "STN": "260", "TG": "136"}, {"YYYYMMDD": "20151110", "STN": "260", "TG": "145"}, {"YYYYMMDD": "20151111", "STN": "260", "TG": "127"}, {"YYYYMMDD": "20151112", "STN": "260", "TG": "133"}, {"YYYYMMDD": "20151113", "STN": "260", "TG": "114"}, {"YYYYMMDD": "20151114", "STN": "260", "TG": "97"}, {"YYYYMMDD": "20151115", "STN": "260", "TG": "143"}, {"YYYYMMDD": "20151116", "STN": "260", "TG": "125"}, {"YYYYMMDD": "20151117", "STN": "260", "TG": "135"}, {"YYYYMMDD": "20151118", "STN": "260", "TG": "131"}, {"YYYYMMDD": "20151119", "STN": "260", "TG": "112"}, {"YYYYMMDD": "20151120", "STN": "260", "TG": "79"}, {"YYYYMMDD": "20151121", "STN": "260", "TG": "43"}, {"YYYYMMDD": "20151122", "STN": "260", "TG": "26"}, {"YYYYMMDD": "20151123", "STN": "260", "TG": "32"}, {"YYYYMMDD": "20151124", "STN": "260", "TG": "42"}, {"YYYYMMDD": "20151125", "STN": "260", "TG": "54"}, {"YYYYMMDD": "20151126", "STN": "260", "TG": "40"}, {"YYYYMMDD": "20151127", "STN": "260", "TG": "45"}, {"YYYYMMDD": "20151128", "STN": "260", "TG": "67"}, {"YYYYMMDD": "20151129", "STN": "260", "TG": "102"}, {"YYYYMMDD": "20151130", "STN": "260", "TG": "95"}, {"YYYYMMDD": "20151201", "STN": "260", "TG": "97"}, {"YYYYMMDD": "20151202", "STN": "260", "TG": "110"}, {"YYYYMMDD": "20151203", "STN": "260", "TG": "98"}, {"YYYYMMDD": "20151204", "STN": "260", "TG": "94"}, {"YYYYMMDD": "20151205", "STN": "260", "TG": "79"}, {"YYYYMMDD": "20151206", "STN": "260", "TG": "105"}, {"YYYYMMDD": "20151207", "STN": "260", "TG": "105"}, {"YYYYMMDD": "20151208", "STN": "260", "TG": "98"}, {"YYYYMMDD": "20151209", "STN": "260", "TG": "76"}, {"YYYYMMDD": "20151210", "STN": "260", "TG": "59"}, {"YYYYMMDD": "20151211", "STN": "260", "TG": "70"}, {"YYYYMMDD": "20151212", "STN": "260", "TG": "76"}, {"YYYYMMDD": "20151213", "STN": "260", "TG": "68"}, {"YYYYMMDD": "20151214", "STN": "260", "TG": "76"}, {"YYYYMMDD": "20151215", "STN": "260", "TG": "74"}, {"YYYYMMDD": "20151216", "STN": "260", "TG": "114"}, {"YYYYMMDD": "20151217", "STN": "260", "TG": "136"}, {"YYYYMMDD": "20151218", "STN": "260", "TG": "118"}, {"YYYYMMDD": "20151219", "STN": "260", "TG": "122"}, {"YYYYMMDD": "20151220", "STN": "260", "TG": "116"}, {"YYYYMMDD": "20151221", "STN": "260", "TG": "104"}, {"YYYYMMDD": "20151222", "STN": "260", "TG": "130"}, {"YYYYMMDD": "20151223", "STN": "260", "TG": "106"}, {"YYYYMMDD": "20151224", "STN": "260", "TG": "98"}, {"YYYYMMDD": "20151225", "STN": "260", "TG": "96"}, {"YYYYMMDD": "20151226", "STN": "260", "TG": "131"}, {"YYYYMMDD": "20151227", "STN": "260", "TG": "118"}, {"YYYYMMDD": "20151228", "STN": "260", "TG": "89"}, {"YYYYMMDD": "20151229", "STN": "260", "TG": "75"}, {"YYYYMMDD": "20151230", "STN": "260", "TG": "69"}, {"YYYYMMDD": "20151231", "STN": "260", "TG": "78"}]